langmem/__init__.py
langmem/errors.py
langmem/graph_rag.py
langmem/reflection.py
langmem/utils.py
langmem/graphs/__init__.py
langmem/graphs/auth.py
langmem/graphs/prompts.py
langmem/graphs/semantic.py
langmem/knowledge/__init__.py
langmem/knowledge/extraction.py
langmem/knowledge/tools.py
langmem/prompts/__init__.py
langmem/prompts/_layers.py
langmem/prompts/gradient.py
langmem/prompts/metaprompt.py
langmem/prompts/optimization.py
langmem/prompts/prompt.py
langmem/prompts/stateful.py
langmem/prompts/stateless.py
langmem/prompts/types.py
langmem/prompts/utils.py
langmem/short_term/__init__.py
langmem/short_term/summarization.py
langmem-0.0.29.dist-info/METADATA
langmem-0.0.29.dist-info/WHEEL
langmem-0.0.29.dist-info/licenses/LICENSE
langmem-0.0.29.dist-info/RECORD
