Metadata-Version: 2.4
Name: langmem
Version: 0.0.29
Summary: Prebuilt utilities for memory management and retrieval.
License: MIT License
License-File: LICENSE
Requires-Python: >=3.10
Requires-Dist: langchain-anthropic>=0.3.3
Requires-Dist: langchain-core>=0.3.46
Requires-Dist: langchain-openai>=0.3.1
Requires-Dist: langchain>=0.3.15
Requires-Dist: langgraph-checkpoint>=2.0.12
Requires-Dist: langgraph<0.7.0,>=0.6.0
Requires-Dist: langsmith>=0.3.8
Requires-Dist: trustcall>=0.0.39
